pyhectiqlab/__init__.py
pyhectiqlab/artifact.py
pyhectiqlab/auth.py
pyhectiqlab/client.py
pyhectiqlab/config.py
pyhectiqlab/const.py
pyhectiqlab/dataset.py
pyhectiqlab/decorators.py
pyhectiqlab/logging.py
pyhectiqlab/message.py
pyhectiqlab/metrics.py
pyhectiqlab/model.py
pyhectiqlab/project.py
pyhectiqlab/run.py
pyhectiqlab/step.py
pyhectiqlab/tag.py
pyhectiqlab/utils.py
pyhectiqlab/versions.py
pyhectiqlab/cli/__init__.py
pyhectiqlab/cli/__main__.py
pyhectiqlab/cli/auth.py
pyhectiqlab/cli/diff.py
pyhectiqlab/functional/__init__.py
pyhectiqlab/functional/artifact.py
pyhectiqlab/functional/block.py
pyhectiqlab/functional/dataset.py
pyhectiqlab/functional/message.py
pyhectiqlab/functional/model.py
pyhectiqlab/functional/project.py
pyhectiqlab/functional/run.py
pyhectiqlab/functional/step.py
pyhectiqlab/functional/tag.py
pyhectiqlab/functional/utils.py
pyhectiqlab/settings/__init__.py
pyhectiqlab-3.1.15.dist-info/METADATA
pyhectiqlab-3.1.15.dist-info/WHEEL
pyhectiqlab-3.1.15.dist-info/entry_points.txt
pyhectiqlab-3.1.15.dist-info/top_level.txt
pyhectiqlab-3.1.15.dist-info/RECORD
