Metadata-Version: 2.4
Name: pyhectiqlab
Version: 3.1.15
Summary: Python client for the Hectiq Lab plateform.
Author-email: Edward Laurence <edwardl@hectiq.ai>, Charles Murphy <cmurphy@hectiq.ai>
Maintainer-email: Edward Laurence <edwardl@hectiq.ai>, Charles Murphy <cmurphy@hectiq.ai>
Project-URL: Repository, https://github.com/HectiqAI/hectiq-lab-revision.git
Requires-Python: >=3.8
Requires-Dist: httpx
Requires-Dist: orjson
Requires-Dist: numpy
Requires-Dist: unicode-slugify>=0.1.5
Requires-Dist: toml
Requires-Dist: GitPython
Requires-Dist: clisync==1.3.2
Requires-Dist: hectiq-config==1.1.0
Requires-Dist: rich
Requires-Dist: ipywidgets
Requires-Dist: packaging>=21.0
Requires-Dist: click
Requires-Dist: pydantic
Requires-Dist: python-dotenv
Requires-Dist: google-cloud-storage
